{
  "version": 1,
  "effects": [
    {
      "name": "RGB Split",
      "effects": [
        {
          "type": "RuntimeMetal:b3d67013-560d-498e-9cb8-c99714ed8b4a",
          "params": {
            "animated": true,
            "offsetAmount": 25
          }
        }
      ]
    },
    {
      "name": "Datamosh: Subtle + RGB",
      "effects": [
        {
          "type": "RuntimeMetal:b3d67013-560d-498e-9cb8-c99714ed8b4a",
          "params": {
            "animated": true,
            "offsetAmount": 12
          }
        }
      ]
    },
    {
      "name": "Hold + Ghost",
      "effects": [
        {
          "type": "RuntimeMetal:478863b3-72a1-443c-b341-dcd13dfa51c3",
          "params": {
            "blurAmount": 0.92,
            "intensity": 0.64,
            "trailLength": 14
          }
        }
      ]
    },
    {
      "name": "Mosh + Ghost",
      "effects": [
        {
          "type": "RuntimeMetal:478863b3-72a1-443c-b341-dcd13dfa51c3",
          "params": {
            "blurAmount": 42,
            "intensity": 0.15,
            "trailLength": 8
          }
        }
      ]
    }
  ]
}
